lakehouse_operators_demo/__init__.py
lakehouse_operators_demo/core.py
lakehouse_operators_demo-0.0.1.dist-info/METADATA
lakehouse_operators_demo-0.0.1.dist-info/WHEEL
lakehouse_operators_demo-0.0.1.dist-info/RECORD
