Metadata-Version: 2.4
Name: lakehouse-operators-demo
Version: 0.0.1
Requires-Dist: fasttext
Requires-Dist: numpy<2.0
